django_celery_fulldbresult/__init__.py
django_celery_fulldbresult/admin.py
django_celery_fulldbresult/errors.py
django_celery_fulldbresult/managers.py
django_celery_fulldbresult/models.py
django_celery_fulldbresult/result_backends.py
django_celery_fulldbresult/serialization.py
django_celery_fulldbresult/tasks.py
django_celery_fulldbresult/tests.py
django_celery_fulldbresult/views.py
django_celery_fulldbresult/management/__init__.py
django_celery_fulldbresult/management/commands/__init__.py
django_celery_fulldbresult/management/commands/find_stale_scheduled_tasks.py
django_celery_fulldbresult/management/commands/find_stale_tasks.py
django_celery_fulldbresult/management/commands/fix_json_results.py
django_celery_fulldbresult/migrations/0001_initial.py
django_celery_fulldbresult/migrations/0002_auto_20150713_1520.py
django_celery_fulldbresult/migrations/0003_taskresultmeta_eta.py
django_celery_fulldbresult/migrations/0004_auto_20150914_1947.py
django_celery_fulldbresult/migrations/0005_scheduling.py
django_celery_fulldbresult/migrations/__init__.py
django_celery_fulldbresult-0.5.3.dist-info/DESCRIPTION.rst
django_celery_fulldbresult-0.5.3.dist-info/METADATA
django_celery_fulldbresult-0.5.3.dist-info/RECORD
django_celery_fulldbresult-0.5.3.dist-info/WHEEL
django_celery_fulldbresult-0.5.3.dist-info/metadata.json
django_celery_fulldbresult-0.5.3.dist-info/top_level.txt
