Metadata-Version: 2.0
Name: django-celery-fulldbresult
Version: 0.5.3
Summary: Celery result backend that stores everything.
Home-page: https://github.com/resulto-admin/django-celery-fulldbresult
Author: Resulto Dev Team
Author-email: dev@resulto.ca
License: New BSD
Keywords: celery django queue
Platform: UNKNOWN
Classifier: Development Status :: 5 - Production/Stable
Classifier: Intended Audience :: Developers
Classifier: Topic :: Communications
Classifier: Topic :: Software Development :: Libraries :: Python Modules
Classifier: Topic :: System :: Distributed Computing
Classifier: License :: OSI Approved :: BSD License
Classifier: Programming Language :: Python :: 2
Classifier: Programming Language :: Python :: 2.7
Classifier: Programming Language :: Python :: 3
Classifier: Programming Language :: Python :: 3.4
Requires-Dist: Django (>=1.7)
Requires-Dist: celery (>=3.1)
Requires-Dist: django-celery (>=3.1.16)
Provides-Extra: test
Requires-Dist: tox (>=2.0.1); extra == 'test'
